bw2simple/__init__.py
bw2simple/activity.py
bw2simple/exchange.py
bw2simple-0.3.1.dist-info/DESCRIPTION.rst
bw2simple-0.3.1.dist-info/METADATA
bw2simple-0.3.1.dist-info/metadata.json
bw2simple-0.3.1.dist-info/RECORD
bw2simple-0.3.1.dist-info/top_level.txt
bw2simple-0.3.1.dist-info/WHEEL
