Metadata-Version: 2.0
Name: bw2simple
Version: 0.3.1
Summary: ('Simple proxies to make command-line life with Brightway2 objects a bit easier.',)
Home-page: https://bitbucket.org/cmutel/brightway2-simple
Author: Chris Mutel
Author-email: cmutel@gmail.com
License: Copyright (c) 2014, Chris Mutel and ETH Zürich
Requires-Dist: brightway2
Requires-Dist: bw2calc (>=0.13)
Requires-Dist: bw2data (>=0.15.1)
Requires-Dist: bw2ui (>=0.12.1)
